femdesign/__init__.py
femdesign/comunication.py
femdesign/database.py
femdesign/calculate/__init__.py
femdesign/calculate/analysis.py
femdesign/calculate/command.py
femdesign/calculate/fdscript.py
femdesign/utilities/__init__.py
femdesign/utilities/filehelper.py
FEM_Design-0.0.7.dist-info/LICENSE
FEM_Design-0.0.7.dist-info/METADATA
FEM_Design-0.0.7.dist-info/WHEEL
FEM_Design-0.0.7.dist-info/top_level.txt
FEM_Design-0.0.7.dist-info/RECORD
