Metadata-Version: 2.1
Name: FEM-Design
Version: 0.0.7
Summary: The FEM-Design API package
Author-email: FEM-Design <femdesign.api@strusoft.com>
Maintainer-email: Marco Pellegrino <marco.pellegrino@strusoft.com>, Illyés Zoltán <sinnach@strusoft.hu>
Project-URL: Homepage, https://femdesign-api-docs.onstrusoft.com
Project-URL: Repository, https://github.com/strusoft/femdesign-api/tree/master/FemDesign.Python
Project-URL: Issues, https://github.com/strusoft/femdesign-api/issues
Keywords: fem,fea,structures,strusoft,FEM-Design API
Classifier: Programming Language :: Python :: 3
Classifier: License :: OSI Approved :: MIT License
Classifier: Operating System :: Microsoft
Requires-Python: >=3.8
License-File: LICENSE
